aws_cdk/mixins_preview/__init__.py
aws_cdk/mixins_preview/py.typed
aws_cdk/mixins_preview/_jsii/__init__.py
aws_cdk/mixins_preview/_jsii/mixins-preview@2.236.0-alpha.0.jsii.tgz
aws_cdk/mixins_preview/alexa_ask/__init__.py
aws_cdk/mixins_preview/alexa_ask/mixins/__init__.py
aws_cdk/mixins_preview/aws_accessanalyzer/__init__.py
aws_cdk/mixins_preview/aws_accessanalyzer/mixins/__init__.py
aws_cdk/mixins_preview/aws_acmpca/__init__.py
aws_cdk/mixins_preview/aws_acmpca/mixins/__init__.py
aws_cdk/mixins_preview/aws_aiops/__init__.py
aws_cdk/mixins_preview/aws_aiops/mixins/__init__.py
aws_cdk/mixins_preview/aws_amazonmq/__init__.py
aws_cdk/mixins_preview/aws_amazonmq/mixins/__init__.py
aws_cdk/mixins_preview/aws_amplify/__init__.py
aws_cdk/mixins_preview/aws_amplify/mixins/__init__.py
aws_cdk/mixins_preview/aws_amplifyuibuilder/__init__.py
aws_cdk/mixins_preview/aws_amplifyuibuilder/mixins/__init__.py
aws_cdk/mixins_preview/aws_apigateway/__init__.py
aws_cdk/mixins_preview/aws_apigateway/mixins/__init__.py
aws_cdk/mixins_preview/aws_apigatewayv2/__init__.py
aws_cdk/mixins_preview/aws_apigatewayv2/mixins/__init__.py
aws_cdk/mixins_preview/aws_appconfig/__init__.py
aws_cdk/mixins_preview/aws_appconfig/mixins/__init__.py
aws_cdk/mixins_preview/aws_appflow/__init__.py
aws_cdk/mixins_preview/aws_appflow/mixins/__init__.py
aws_cdk/mixins_preview/aws_appintegrations/__init__.py
aws_cdk/mixins_preview/aws_appintegrations/mixins/__init__.py
aws_cdk/mixins_preview/aws_applicationautoscaling/__init__.py
aws_cdk/mixins_preview/aws_applicationautoscaling/mixins/__init__.py
aws_cdk/mixins_preview/aws_applicationinsights/__init__.py
aws_cdk/mixins_preview/aws_applicationinsights/mixins/__init__.py
aws_cdk/mixins_preview/aws_applicationsignals/__init__.py
aws_cdk/mixins_preview/aws_applicationsignals/mixins/__init__.py
aws_cdk/mixins_preview/aws_appmesh/__init__.py
aws_cdk/mixins_preview/aws_appmesh/mixins/__init__.py
aws_cdk/mixins_preview/aws_apprunner/__init__.py
aws_cdk_mixins_preview-2.236.0a0.dist-info/LICENSE
aws_cdk_mixins_preview-2.236.0a0.dist-info/METADATA
aws_cdk_mixins_preview-2.236.0a0.dist-info/NOTICE
aws_cdk_mixins_preview-2.236.0a0.dist-info/WHEEL
aws_cdk_mixins_preview-2.236.0a0.dist-info/top_level.txt
aws_cdk_mixins_preview-2.236.0a0.dist-info/RECORD
